MANIFEST.in
README.md
setup.py
spider163/__init__.py
spider163/settings.py
spider163/version.py
spider163.egg-info/PKG-INFO
spider163.egg-info/SOURCES.txt
spider163.egg-info/dependency_links.txt
spider163.egg-info/entry_points.txt
spider163.egg-info/not-zip-safe
spider163.egg-info/requires.txt
spider163.egg-info/top_level.txt
spider163/bin/__init__.py
spider163/bin/cli.py
spider163/bin/cli_test.py
spider163/spider/__init__.py
spider163/spider/authorize.py
spider163/spider/comment.py
spider163/spider/lyric.py
spider163/spider/mp3.py
spider163/spider/music.py
spider163/spider/playlist.py
spider163/spider/public.py
spider163/spider/read.py
spider163/spider/search.py
spider163/template/spider163.conf
spider163/utils/__init__.py
spider163/utils/config.py
spider163/utils/const.py
spider163/utils/encrypt.py
spider163/utils/healthz.py
spider163/utils/pylog.py
spider163/utils/pysql.py
spider163/utils/tools.py
spider163/www/__init__.py
spider163/www/web.py
spider163/www/static/.DS_Store
spider163/www/static/css/spider163.css
spider163/www/static/img/.DS_Store
spider163/www/static/img/weixin.jpeg
spider163/www/static/img/zhifubao.jpeg
spider163/www/static/js/echarts.min.js
spider163/www/static/js/macarons.js
spider163/www/static/js/scan.js
spider163/www/static/js/spider163.js
spider163/www/static/js/stat.js
spider163/www/templates/bussiness.html
spider163/www/templates/index.html
spider163/www/templates/scan.html
spider163/www/templates/spider.html
spider163/www/templates/stat.html