Metadata-Version: 1.1
Name: spider163
Version: 2.7.6
Summary: 简单易用、功能强大的网易云音乐爬虫
Home-page: https://github.com/Chengyumeng/spider163
Author: ChengTian
Author-email: 792400644@qq.com
License: MIT License
Platform: UNKNOWN
Classifier: Development Status :: 5 - Production/Stable
Classifier: Environment :: Console
Classifier: Environment :: Web Environment
Classifier: Programming Language :: Python :: 2.7
Classifier: Programming Language :: Python :: 3.4
